Workbook
Name NativeTimeline_Order_Date: #N/A
Name Sales_data: Sales_Data_1[]
Name Slicer_Delivery_Status: #N/A
Name Slicer_Payment_Mode: #N/A
Name Slicer_Product_Category: #N/A
Name Slicer_Region: #N/A

Sheet Raw data
A1: OrderID | B1: Order_Date | C1: Customer_Name | D1: Region | E1: Country | F1: City | G1: Product_Category | H1: Sub_Category | I1: Product_Name | J1: Quantity | K1: Unit_Price | L1: Discount | M1: Discounted_Price | N1: Sales | O1: Profit_Margin | P1: Profit_Amount | Q1: Payment_Mode | R1: Delivery_Status | S1: Delivery_Days
A2: ORD1000 | B2: 44927 | C2: Sara Khan | D2: South | E2: USA | F2: London | G2: Sports | H2: Yoga Mat | I2: Yoga Mat - 475 | J2: 8 | K2: 10078 | L2: 0.18 | M2: ='Raw data'!$K2*(1- 'Raw data'!$L2) -> 8263.96 | N2: 66111.68 | O2: 0.25 | P2: 16527.92 | Q2: UPI | R2: Cancelled | S2: 9
A3: ORD1001 | B3: 44928 | C3: Amit Verma | D3: West | E3: UK | F3: Bangalore | G3: Books | H3: Biography | I3: Biography - 186 | J3: 2 | K3: 627 | L3: 0.18 | M3: ='Raw data'!$K3*(1- 'Raw data'!$L3) -> 514.14 | N3: 1028.28 | O3: 0.4 | P3: 411.31 | Q3: Cash | R3: Pending | S3: 5
A4: ORD1002 | B4: 44929 | C4: Priya Mehta | D4: East | E4: Canada | F4: Toronto | G4: Clothing | H4: Dress | I4: Dress - 518 | J4: 4 | K4: 2395 | L4: 0.14 | M4: ='Raw data'!$K4*(1- 'Raw data'!$L4) -> 2059.7 | N4: 8238.8 | O4: 0.35 | P4: 2883.58 | Q4: Debit Card | R4: Delivered | S4: 6
A5: ORD1003 | B5: 44930 | C5: Sara Khan | D5: East | E5: USA | F5: Toronto | G5: Books | H5: Biography | I5: Biography - 853 | J5: 6 | K5: 516 | L5: 0.24 | M5: ='Raw data'!$K5*(1- 'Raw data'!$L5) -> 392.16 | N5: 2352.96 | O5: 0.4 | P5: 941.18 | Q5: Credit Card | R5: Pending | S5: 9
A6: ORD1004 | B6: 44931 | C6: Sara Khan | D6: South | E6: UK | F6: London | G6: Books | H6: Biography | I6: Biography - 298 | J6: 2 | K6: 834 | L6: 0.12 | M6: ='Raw data'!$K6*(1- 'Raw data'!$L6) -> 733.92 | N6: 1467.84 | O6: 0.4 | P6: 587.14 | Q6: Cash | R6: Delivered | S6: 9
A7: ORD1005 | B7: 44932 | C7: David Lee | D7: North | E7: Canada | F7: Bangalore | G7: Furniture | H7: Chair | I7: Chair - 562 | J7: 7 | K7: 3925 | L7: 0.1 | M7: ='Raw data'!$K7*(1- 'Raw data'!$L7) -> 3532.5 | N7: 24727.5 | O7: 0.2 | P7: 4945.5 | Q7: UPI | R7: Delivered | S7: 8
A8: ORD1006 | B8: 44933 | C8: Sara Khan | D8: South | E8: Canada | F8: London | G8: Clothing | H8: Dress | I8: Dress - 536 | J8: 3 | K8: 2556 | L8: 0.04 | M8: ='Raw data'!$K8*(1- 'Raw data'!$L8) -> 2453.76 | N8: 7361.28 | O8: 0.35 | P8: 2576.45 | Q8: Cash | R8: Delivered | S8: 9
A9: ORD1007 | B9: 44934 | C9: Maria Singh | D9: East | E9: USA | F9: Bangalore | G9: Clothing | H9: T-Shirt | I9: T-Shirt - 409 | J9: 3 | K9: 3644 | L9: 0.2 | M9: ='Raw data'!$K9*(1- 'Raw data'!$L9) -> 2915.2 | N9: 8745.6 | O9: 0.35 | P9: 3060.96 | Q9: UPI | R9: Pending | S9: 4
A10: ORD1008 | B10: 44935 | C10: Priya Mehta | D10: South | E10: India | F10: Delhi | G10: Clothing | H10: Dress | I10: Dress - 695 | J10: 2 | K10: 2770 | L10: 0.18 | M10: ='Raw data'!$K10*(1- 'Raw data'!$L10) -> 2271.4 | N10: 4542.8 | O10: 0.35 | P10: 1589.98 | Q10: Debit Card | R10: Delivered | S10: 6
A11: ORD1009 | B11: 44936 | C11: Priya Mehta | D11: West | E11: India | F11: London | G11: Books | H11: Comics | I11: Comics - 853 | J11: 8 | K11: 752 | L11: 0.1 | M11: ='Raw data'!$K11*(1- 'Raw data'!$L11) -> 676.8 | N11: 5414.4 | O11: 0.4 | P11: 2165.76 | Q11: Cash | R11: Delivered | S11: 5
A12: ORD1010 | B12: 44937 | C12: Amit Verma | D12: North | E12: USA | F12: Bangalore | G12: Sports | H12: Football | I12: Football - 380 | J12: 6 | K12: 9907 | L12: 0.01 | M12: ='Raw data'!$K12*(1- 'Raw data'!$L12) -> 9807.93 | N12: 58847.58 | O12: 0.25 | P12: 14711.9 | Q12: Debit Card | R12: Delivered | S12: 5
A13: ORD1011 | B13: 44938 | C13: Amit Verma | D13: South | E13: Canada | F13: Toronto | G13: Clothing | H13: T-Shirt | I13: T-Shirt - 422 | J13: 1 | K13: 4411 | L13: 0.21 | M13: ='Raw data'!$K13*(1- 'Raw data'!$L13) -> 3484.69 | N13: 3484.69 | O13: 0.35 | P13: 1219.64 | Q13: Credit Card | R13: Delivered | S13: 4
... A1001: ORD1999 | B1001: 45926 | C1001: Maria Singh | D1001: South | E1001: USA | F1001: Delhi | G1001: Clothing | H1001: Jeans | I1001: Jeans - 576 | J1001: 1 | K1001: 2785 | L1001: 0 | M1001: ='Raw data'!$K1001*(1- 'Raw data'!$L1001) -> 2785 | N1001: 2785 | O1001: 0.35 | P1001: 974.75 | Q1001: UPI | R1001: Delivered | S1001: 8

Sheet Raw_DATA
A1: OrderID | B1: Order_Date | C1: Customer_Name | D1: Region | E1: Country | F1: City | G1: Product_Category | H1: Sub_Category | I1: Product_Name | J1: Quantity | K1: Unit_Price | L1: Discount | M1: Discounted_Price | N1: Sales | O1: Profit_Margin | P1: Profit_Amount | Q1: Payment_Mode | R1: Delivery_Status | S1: Delivery_Days | T1: Order_Year | U1: Order_Month_Name | V1: Order_Month_Number | W1: Order_Year_Month | X1: Total_Cost | Y1: Delivery_Performance | Z1: Profitability_Status | AA1: Order_Size_Tier
A2: Ord1309 | B2: 45236 | C2: Sara Khan | D2: North | E2: Uk | F2: New York | G2: Books | H2: Fiction | I2: Fiction - 144 | J2: 1 | K2: 358 | L2: 0.21 | M2: 282.82 | N2: 282.82 | O2: 0.4 | P2: 113.13 | Q2: Credit Card | R2: Delivered | S2: 4 | T2: =YEAR(Sales_Data_1[[#This Row],[Order_Date]]) -> 2023 | U2: =TEXT(Sales_Data_1[[#This Row],[Order_Date]], "mmm") -> Nov | V2: =MONTH(Sales_Data_1[[#This Row],[Order_Date]]) -> 11 | W2: =TEXT(Sales_Data_1[[#This Row],[Order_Date]], "yyyy-mm") -> 2023-11 | X2: =Sales_Data_1[[#This Row],[Sales]]-Sales_Data_1[[#This Row],[Profit_Amount]] -> 169.69 | Y2: {=_xlfn.IFS(Sales_Data_1[[#This Row],[Delivery_Days]]<=3, "Fast", Sales_Data_1[[#This Row],[Delivery_Days]]<= 7, "Standard", TRUE, "Delayed")} -> Standard | Z2: {=_xlfn.IFS(Sales_Data_1[[#This Row],[Profit_Amount]]> 0, "Profitable", Sales_Data_1[[#This Row],[Profit_Amount]] = 0, "Break-Even", TRUE, "Loss")} -> Profitable | AA2: {=_xlfn.IFS(Sales_Data_1[[#This Row],[Sales]]>= 1000, "High Value", Sales_Data_1[[#This Row],[Sales]]>= 300, "Mid Value", TRUE, "Low Value")} -> Low Value
A3: Ord1666 | B3: 45593 | C3: John Smith | D3: North | E3: Uk | F3: Bangalore | G3: Books | H3: Biography | I3: Biography - 889 | J3: 1 | K3: 348 | L3: 0.04 | M3: 334.08 | N3: 334.08 | O3: 0.4 | P3: 133.63 | Q3: Debit Card | R3: Pending | S3: 1 | T3: =YEAR(Sales_Data_1[[#This Row],[Order_Date]]) -> 2024 | U3: =TEXT(Sales_Data_1[[#This Row],[Order_Date]], "mmm") -> Oct | V3: =MONTH(Sales_Data_1[[#This Row],[Order_Date]]) -> 10 | W3: =TEXT(Sales_Data_1[[#This Row],[Order_Date]], "yyyy-mm") -> 2024-10 | X3: =Sales_Data_1[[#This Row],[Sales]]-Sales_Data_1[[#This Row],[Profit_Amount]] -> 200.45 | Y3: {=_xlfn.IFS(Sales_Data_1[[#This Row],[Delivery_Days]]<=3, "Fast", Sales_Data_1[[#This Row],[Delivery_Days]]<= 7, "Standard", TRUE, "Delayed")} -> Fast | Z3: {=_xlfn.IFS(Sales_Data_1[[#This Row],[Profit_Amount]]> 0, "Profitable", Sales_Data_1[[#This Row],[Profit_Amount]] = 0, "Break-Even", TRUE, "Loss")} -> Profitable | AA3: {=_xlfn.IFS(Sales_Data_1[[#This Row],[Sales]]>= 1000, "High Value", Sales_Data_1[[#This Row],[Sales]]>= 300, "Mid Value", TRUE, "Low Value")} -> Mid Value
A4: Ord1803 | B4: 45730 | C4: David Lee | D4: East | E4: Canada | F4: Mumbai | G4: Books | H4: Biography | I4: Biography - 493 | J4: 2 | K4: 218 | L4: 0.04 | M4: 209.28 | N4: 418.56 | O4: 0.4 | P4: 167.42 | Q4: Debit Card | R4: Delivered | S4: 6 | T4: =YEAR(Sales_Data_1[[#This Row],[Order_Date]]) -> 2025 | U4: =TEXT(Sales_Data_1[[#This Row],[Order_Date]], "mmm") -> Mar | V4: =MONTH(Sales_Data_1[[#This Row],[Order_Date]]) -> 3 | W4: =TEXT(Sales_Data_1[[#This Row],[Order_Date]], "yyyy-mm") -> 2025-03 | X4: =Sales_Data_1[[#This Row],[Sales]]-Sales_Data_1[[#This Row],[Profit_Amount]] -> 251.14 | Y4: {=_xlfn.IFS(Sales_Data_1[[#This Row],[Delivery_Days]]<=3, "Fast", Sales_Data_1[[#This Row],[Delivery_Days]]<= 7, "Standard", TRUE, "Delayed")} -> Standard | Z4: {=_xlfn.IFS(Sales_Data_1[[#This Row],[Profit_Amount]]> 0, "Profitable", Sales_Data_1[[#This Row],[Profit_Amount]] = 0, "Break-Even", TRUE, "Loss")} -> Profitable | AA4: {=_xlfn.IFS(Sales_Data_1[[#This Row],[Sales]]>= 1000, "High Value", Sales_Data_1[[#This Row],[Sales]]>= 300, "Mid Value", TRUE, "Low Value")} -> Mid Value
A5: Ord1743 | B5: 45670 | C5: John Smith | D5: East | E5: India | F5: Toronto | G5: Books | H5: Biography | I5: Biography - 551 | J5: 1 | K5: 501 | L5: 0.07 | M5: 465.93 | N5: 465.93 | O5: 0.4 | P5: 186.37 | Q5: Credit Card | R5: Delivered | S5: 6 | T5: =YEAR(Sales_Data_1[[#This Row],[Order_Date]]) -> 2025 | U5: =TEXT(Sales_Data_1[[#This Row],[Order_Date]], "mmm") -> Jan | V5: =MONTH(Sales_Data_1[[#This Row],[Order_Date]]) -> 1 | W5: =TEXT(Sales_Data_1[[#This Row],[Order_Date]], "yyyy-mm") -> 2025-01 | X5: =Sales_Data_1[[#This Row],[Sales]]-Sales_Data_1[[#This Row],[Profit_Amount]] -> 279.56 | Y5: {=_xlfn.IFS(Sales_Data_1[[#This Row],[Delivery_Days]]<=3, "Fast", Sales_Data_1[[#This Row],[Delivery_Days]]<= 7, "Standard", TRUE, "Delayed")} -> Standard | Z5: {=_xlfn.IFS(Sales_Data_1[[#This Row],[Profit_Amount]]> 0, "Profitable", Sales_Data_1[[#This Row],[Profit_Amount]] = 0, "Break-Even", TRUE, "Loss")} -> Profitable | AA5: {=_xlfn.IFS(Sales_Data_1[[#This Row],[Sales]]>= 1000, "High Value", Sales_Data_1[[#This Row],[Sales]]>= 300, "Mid Value", TRUE, "Low Value")} -> Mid Value
A6: Ord1529 | B6: 45456 | C6: John Smith | D6: West | E6: Canada | F6: London | G6: Books | H6: Biography | I6: Biography - 934 | J6: 2 | K6: 282 | L6: 0.16 | M6: 236.88 | N6: 473.76 | O6: 0.4 | P6: 189.5 | Q6: Credit Card | R6: Pending | S6: 4 | T6: =YEAR(Sales_Data_1[[#This Row],[Order_Date]]) -> 2024 | U6: =TEXT(Sales_Data_1[[#This Row],[Order_Date]], "mmm") -> Jun | V6: =MONTH(Sales_Data_1[[#This Row],[Order_Date]]) -> 6 | W6: =TEXT(Sales_Data_1[[#This Row],[Order_Date]], "yyyy-mm") -> 2024-06 | X6: =Sales_Data_1[[#This Row],[Sales]]-Sales_Data_1[[#This Row],[Profit_Amount]] -> 284.26 | Y6: {=_xlfn.IFS(Sales_Data_1[[#This Row],[Delivery_Days]]<=3, "Fast", Sales_Data_1[[#This Row],[Delivery_Days]]<= 7, "Standard", TRUE, "Delayed")} -> Standard | Z6: {=_xlfn.IFS(Sales_Data_1[[#This Row],[Profit_Amount]]> 0, "Profitable", Sales_Data_1[[#This Row],[Profit_Amount]] = 0, "Break-Even", TRUE, "Loss")} -> Profitable | AA6: {=_xlfn.IFS(Sales_Data_1[[#This Row],[Sales]]>= 1000, "High Value", Sales_Data_1[[#This Row],[Sales]]>= 300, "Mid Value", TRUE, "Low Value")} -> Mid Value
A7: Ord1963 | B7: 45890 | C7: Amit Verma | D7: North | E7: Usa | F7: Bangalore | G7: Books | H7: Non-Fiction | I7: Non-Fiction - 265 | J7: 1 | K7: 575 | L7: 0.17 | M7: 477.25 | N7: 477.25 | O7: 0.4 | P7: 190.9 | Q7: Cash | R7: Delivered | S7: 8 | T7: =YEAR(Sales_Data_1[[#This Row],[Order_Date]]) -> 2025 | U7: =TEXT(Sales_Data_1[[#This Row],[Order_Date]], "mmm") -> Aug | V7: =MONTH(Sales_Data_1[[#This Row],[Order_Date]]) -> 8 | W7: =TEXT(Sales_Data_1[[#This Row],[Order_Date]], "yyyy-mm") -> 2025-08 | X7: =Sales_Data_1[[#This Row],[Sales]]-Sales_Data_1[[#This Row],[Profit_Amount]] -> 286.35 | Y7: {=_xlfn.IFS(Sales_Data_1[[#This Row],[Delivery_Days]]<=3, "Fast", Sales_Data_1[[#This Row],[Delivery_Days]]<= 7, "Standard", TRUE, "Delayed")} -> Delayed | Z7: {=_xlfn.IFS(Sales_Data_1[[#This Row],[Profit_Amount]]> 0, "Profitable", Sales_Data_1[[#This Row],[Profit_Amount]] = 0, "Break-Even", TRUE, "Loss")} -> Profitable | AA7: {=_xlfn.IFS(Sales_Data_1[[#This Row],[Sales]]>= 1000, "High Value", Sales_Data_1[[#This Row],[Sales]]>= 300, "Mid Value", TRUE, "Low Value")} -> Mid Value
A8: Ord1381 | B8: 45308 | C8: Maria Singh | D8: South | E8: Uk | F8: Toronto | G8: Books | H8: Biography | I8: Biography - 551 | J8: 1 | K8: 552 | L8: 0.07 | M8: 513.36 | N8: 513.36 | O8: 0.4 | P8: 205.34 | Q8: Cash | R8: Delivered | S8: 6 | T8: =YEAR(Sales_Data_1[[#This Row],[Order_Date]]) -> 2024 | U8: =TEXT(Sales_Data_1[[#This Row],[Order_Date]], "mmm") -> Jan | V8: =MONTH(Sales_Data_1[[#This Row],[Order_Date]]) -> 1 | W8: =TEXT(Sales_Data_1[[#This Row],[Order_Date]], "yyyy-mm") -> 2024-01 | X8: =Sales_Data_1[[#This Row],[Sales]]-Sales_Data_1[[#This Row],[Profit_Amount]] -> 308.02 | Y8: {=_xlfn.IFS(Sales_Data_1[[#This Row],[Delivery_Days]]<=3, "Fast", Sales_Data_1[[#This Row],[Delivery_Days]]<= 7, "Standard", TRUE, "Delayed")} -> Standard | Z8: {=_xlfn.IFS(Sales_Data_1[[#This Row],[Profit_Amount]]> 0, "Profitable", Sales_Data_1[[#This Row],[Profit_Amount]] = 0, "Break-Even", TRUE, "Loss")} -> Profitable | AA8: {=_xlfn.IFS(Sales_Data_1[[#This Row],[Sales]]>= 1000, "High Value", Sales_Data_1[[#This Row],[Sales]]>= 300, "Mid Value", TRUE, "Low Value")} -> Mid Value
A9: Ord1603 | B9: 45530 | C9: David Lee | D9: North | E9: Usa | F9: Toronto | G9: Sports | H9: Football | I9: Football - 240 | J9: 1 | K9: 1016 | L9: 0.19 | M9: 822.96 | N9: 822.96 | O9: 0.25 | P9: 205.74 | Q9: Debit Card | R9: Delivered | S9: 1 | T9: =YEAR(Sales_Data_1[[#This Row],[Order_Date]]) -> 2024 | U9: =TEXT(Sales_Data_1[[#This Row],[Order_Date]], "mmm") -> Aug | V9: =MONTH(Sales_Data_1[[#This Row],[Order_Date]]) -> 8 | W9: =TEXT(Sales_Data_1[[#This Row],[Order_Date]], "yyyy-mm") -> 2024-08 | X9: =Sales_Data_1[[#This Row],[Sales]]-Sales_Data_1[[#This Row],[Profit_Amount]] -> 617.22 | Y9: {=_xlfn.IFS(Sales_Data_1[[#This Row],[Delivery_Days]]<=3, "Fast", Sales_Data_1[[#This Row],[Delivery_Days]]<= 7, "Standard", TRUE, "Delayed")} -> Fast | Z9: {=_xlfn.IFS(Sales_Data_1[[#This Row],[Profit_Amount]]> 0, "Profitable", Sales_Data_1[[#This Row],[Profit_Amount]] = 0, "Break-Even", TRUE, "Loss")} -> Profitable | AA9: {=_xlfn.IFS(Sales_Data_1[[#This Row],[Sales]]>= 1000, "High Value", Sales_Data_1[[#This Row],[Sales]]>= 300, "Mid Value", TRUE, "Low Value")} -> Mid Value
A10: Ord1115 | B10: 45042 | C10: Amit Verma | D10: North | E10: Usa | F10: Delhi | G10: Books | H10: Non-Fiction | I10: Non-Fiction - 673 | J10: 1 | K10: 659 | L10: 0.18 | M10: 540.38 | N10: 540.38 | O10: 0.4 | P10: 216.15 | Q10: Credit Card | R10: Delivered | S10: 5 | T10: =YEAR(Sales_Data_1[[#This Row],[Order_Date]]) -> 2023 | U10: =TEXT(Sales_Data_1[[#This Row],[Order_Date]], "mmm") -> Apr | V10: =MONTH(Sales_Data_1[[#This Row],[Order_Date]]) -> 4 | W10: =TEXT(Sales_Data_1[[#This Row],[Order_Date]], "yyyy-mm") -> 2023-04 | X10: =Sales_Data_1[[#This Row],[Sales]]-Sales_Data_1[[#This Row],[Profit_Amount]] -> 324.23 | Y10: {=_xlfn.IFS(Sales_Data_1[[#This Row],[Delivery_Days]]<=3, "Fast", Sales_Data_1[[#This Row],[Delivery_Days]]<= 7, "Standard", TRUE, "Delayed")} -> Standard | Z10: {=_xlfn.IFS(Sales_Data_1[[#This Row],[Profit_Amount]]> 0, "Profitable", Sales_Data_1[[#This Row],[Profit_Amount]] = 0, "Break-Even", TRUE, "Loss")} -> Profitable | AA10: {=_xlfn.IFS(Sales_Data_1[[#This Row],[Sales]]>= 1000, "High Value", Sales_Data_1[[#This Row],[Sales]]>= 300, "Mid Value", TRUE, "Low Value")} -> Mid Value
A11: Ord1071 | B11: 44998 | C11: David Lee | D11: East | E11: India | F11: Toronto | G11: Books | H11: Comics | I11: Comics - 276 | J11: 1 | K11: 619 | L11: 0.11 | M11: 550.91 | N11: 550.91 | O11: 0.4 | P11: 220.36 | Q11: Credit Card | R11: Delivered | S11: 9 | T11: =YEAR(Sales_Data_1[[#This Row],[Order_Date]]) -> 2023 | U11: =TEXT(Sales_Data_1[[#This Row],[Order_Date]], "mmm") -> Mar | V11: =MONTH(Sales_Data_1[[#This Row],[Order_Date]]) -> 3 | W11: =TEXT(Sales_Data_1[[#This Row],[Order_Date]], "yyyy-mm") -> 2023-03 | X11: =Sales_Data_1[[#This Row],[Sales]]-Sales_Data_1[[#This Row],[Profit_Amount]] -> 330.55 | Y11: {=_xlfn.IFS(Sales_Data_1[[#This Row],[Delivery_Days]]<=3, "Fast", Sales_Data_1[[#This Row],[Delivery_Days]]<= 7, "Standard", TRUE, "Delayed")} -> Delayed | Z11: {=_xlfn.IFS(Sales_Data_1[[#This Row],[Profit_Amount]]> 0, "Profitable", Sales_Data_1[[#This Row],[Profit_Amount]] = 0, "Break-Even", TRUE, "Loss")} -> Profitable | AA11: {=_xlfn.IFS(Sales_Data_1[[#This Row],[Sales]]>= 1000, "High Value", Sales_Data_1[[#This Row],[Sales]]>= 300, "Mid Value", TRUE, "Low Value")} -> Mid Value
A12: Ord1902 | B12: 45829 | C12: John Smith | D12: West | E12: Usa | F12: Toronto | G12: Books | H12: Fiction | I12: Fiction - 965 | J12: 1 | K12: 691 | L12: 0.17 | M12: 573.53 | N12: 573.53 | O12: 0.4 | P12: 229.41 | Q12: Credit Card | R12: Delivered | S12: 9 | T12: =YEAR(Sales_Data_1[[#This Row],[Order_Date]]) -> 2025 | U12: =TEXT(Sales_Data_1[[#This Row],[Order_Date]], "mmm") -> Jun | V12: =MONTH(Sales_Data_1[[#This Row],[Order_Date]]) -> 6 | W12: =TEXT(Sales_Data_1[[#This Row],[Order_Date]], "yyyy-mm") -> 2025-06 | X12: =Sales_Data_1[[#This Row],[Sales]]-Sales_Data_1[[#This Row],[Profit_Amount]] -> 344.12 | Y12: {=_xlfn.IFS(Sales_Data_1[[#This Row],[Delivery_Days]]<=3, "Fast", Sales_Data_1[[#This Row],[Delivery_Days]]<= 7, "Standard", TRUE, "Delayed")} -> Delayed | Z12: {=_xlfn.IFS(Sales_Data_1[[#This Row],[Profit_Amount]]> 0, "Profitable", Sales_Data_1[[#This Row],[Profit_Amount]] = 0, "Break-Even", TRUE, "Loss")} -> Profitable | AA12: {=_xlfn.IFS(Sales_Data_1[[#This Row],[Sales]]>= 1000, "High Value", Sales_Data_1[[#This Row],[Sales]]>= 300, "Mid Value", TRUE, "Low Value")} -> Mid Value
A13: Ord1412 | B13: 45339 | C13: Sara Khan | D13: North | E13: India | F13: Mumbai | G13: Books | H13: Biography | I13: Biography - 522 | J13: 2 | K13: 315 | L13: 0.05 | M13: 299.25 | N13: 598.5 | O13: 0.4 | P13: 239.4 | Q13: Cash | R13: Delivered | S13: 9 | T13: =YEAR(Sales_Data_1[[#This Row],[Order_Date]]) -> 2024 | U13: =TEXT(Sales_Data_1[[#This Row],[Order_Date]], "mmm") -> Feb | V13: =MONTH(Sales_Data_1[[#This Row],[Order_Date]]) -> 2 | W13: =TEXT(Sales_Data_1[[#This Row],[Order_Date]], "yyyy-mm") -> 2024-02 | X13: =Sales_Data_1[[#This Row],[Sales]]-Sales_Data_1[[#This Row],[Profit_Amount]] -> 359.1 | Y13: {=_xlfn.IFS(Sales_Data_1[[#This Row],[Delivery_Days]]<=3, "Fast", Sales_Data_1[[#This Row],[Delivery_Days]]<= 7, "Standard", TRUE, "Delayed")} -> Delayed | Z13: {=_xlfn.IFS(Sales_Data_1[[#This Row],[Profit_Amount]]> 0, "Profitable", Sales_Data_1[[#This Row],[Profit_Amount]] = 0, "Break-Even", TRUE, "Loss")} -> Profitable | AA13: {=_xlfn.IFS(Sales_Data_1[[#This Row],[Sales]]>= 1000, "High Value", Sales_Data_1[[#This Row],[Sales]]>= 300, "Mid Value", TRUE, "Low Value")} -> Mid Value
... A1001: Ord1388 | B1001: 45315 | C1001: Sara Khan | D1001: East | E1001: India | F1001: London | G1001: Electronics | H1001: Laptop | I1001: Laptop - 328 | J1001: 9 | K1001: 78008 | L1001: 0.13 | M1001: 67866.96 | N1001: 610802.64 | O1001: 0.15 | P1001: 91620.4 | Q1001: Cash | R1001: Delivered | S1001: 5 | T1001: =YEAR(Sales_Data_1[[#This Row],[Order_Date]]) -> 2024 | U1001: =TEXT(Sales_Data_1[[#This Row],[Order_Date]], "mmm") -> Jan | V1001: =MONTH(Sales_Data_1[[#This Row],[Order_Date]]) -> 1 | W1001: =TEXT(Sales_Data_1[[#This Row],[Order_Date]], "yyyy-mm") -> 2024-01 | X1001: =Sales_Data_1[[#This Row],[Sales]]-Sales_Data_1[[#This Row],[Profit_Amount]] -> 519182.24 | Y1001: {=_xlfn.IFS(Sales_Data_1[[#This Row],[Delivery_Days]]<=3, "Fast", Sales_Data_1[[#This Row],[Delivery_Days]]<= 7, "Standard", TRUE, "Delayed")} -> Standard | Z1001: {=_xlfn.IFS(Sales_Data_1[[#This Row],[Profit_Amount]]> 0, "Profitable", Sales_Data_1[[#This Row],[Profit_Amount]] = 0, "Break-Even", TRUE, "Loss")} -> Profitable | AA1001: {=_xlfn.IFS(Sales_Data_1[[#This Row],[Sales]]>= 1000, "High Value", Sales_Data_1[[#This Row],[Sales]]>= 300, "Mid Value", TRUE, "Low Value")} -> High Value

Sheet Processed_DATA
A1: OrderID | B1: Order_Date | C1: Customer_Name | D1: Region | E1: Country | F1: City | G1: Product_Category | H1: Sub_Category | I1: Product_Name | J1: Quantity | K1: Unit_Price | L1: Discount | M1: Discounted_Price | N1: Sales | O1: Profit_Margin | P1: Profit_Amount | Q1: Payment_Mode | R1: Delivery_Status | S1: Delivery_Days | T1: Order_Year | U1: Order_Month_Name | V1: Order_Month_Number | W1: Order_Year_Month | X1: Total_Cost | Y1: Delivery_Performance | Z1: Profitability_Status | AA1: Order_Size_Tier
A2: Ord1309 | B2: 45236 | C2: Sara Khan | D2: North | E2: Uk | F2: New York | G2: Books | H2: Fiction | I2: Fiction - 144 | J2: 1 | K2: 358 | L2: 0.21 | M2: 282.82 | N2: 282.82 | O2: 0.4 | P2: 113.13 | Q2: Credit Card | R2: Delivered | S2: 4 | T2: 2023 | U2: Nov | V2: 11 | W2: 2023-11 | X2: 169.69 | Y2: Standard | Z2: Profitable | AA2: Low Value
A3: Ord1666 | B3: 45593 | C3: John Smith | D3: North | E3: Uk | F3: Bangalore | G3: Books | H3: Biography | I3: Biography - 889 | J3: 1 | K3: 348 | L3: 0.04 | M3: 334.08 | N3: 334.08 | O3: 0.4 | P3: 133.63 | Q3: Debit Card | R3: Pending | S3: 1 | T3: 2024 | U3: Oct | V3: 10 | W3: 2024-10 | X3: 200.45 | Y3: Fast | Z3: Profitable | AA3: Mid Value
A4: Ord1803 | B4: 45730 | C4: David Lee | D4: East | E4: Canada | F4: Mumbai | G4: Books | H4: Biography | I4: Biography - 493 | J4: 2 | K4: 218 | L4: 0.04 | M4: 209.28 | N4: 418.56 | O4: 0.4 | P4: 167.42 | Q4: Debit Card | R4: Delivered | S4: 6 | T4: 2025 | U4: Mar | V4: 3 | W4: 2025-03 | X4: 251.14 | Y4: Standard | Z4: Profitable | AA4: Mid Value
A5: Ord1743 | B5: 45670 | C5: John Smith | D5: East | E5: India | F5: Toronto | G5: Books | H5: Biography | I5: Biography - 551 | J5: 1 | K5: 501 | L5: 0.07 | M5: 465.93 | N5: 465.93 | O5: 0.4 | P5: 186.37 | Q5: Credit Card | R5: Delivered | S5: 6 | T5: 2025 | U5: Jan | V5: 1 | W5: 2025-01 | X5: 279.56 | Y5: Standard | Z5: Profitable | AA5: Mid Value
A6: Ord1529 | B6: 45456 | C6: John Smith | D6: West | E6: Canada | F6: London | G6: Books | H6: Biography | I6: Biography - 934 | J6: 2 | K6: 282 | L6: 0.16 | M6: 236.88 | N6: 473.76 | O6: 0.4 | P6: 189.5 | Q6: Credit Card | R6: Pending | S6: 4 | T6: 2024 | U6: Jun | V6: 6 | W6: 2024-06 | X6: 284.26 | Y6: Standard | Z6: Profitable | AA6: Mid Value
A7: Ord1963 | B7: 45890 | C7: Amit Verma | D7: North | E7: Usa | F7: Bangalore | G7: Books | H7: Non-Fiction | I7: Non-Fiction - 265 | J7: 1 | K7: 575 | L7: 0.17 | M7: 477.25 | N7: 477.25 | O7: 0.4 | P7: 190.9 | Q7: Cash | R7: Delivered | S7: 8 | T7: 2025 | U7: Aug | V7: 8 | W7: 2025-08 | X7: 286.35 | Y7: Delayed | Z7: Profitable | AA7: Mid Value
A8: Ord1381 | B8: 45308 | C8: Maria Singh | D8: South | E8: Uk | F8: Toronto | G8: Books | H8: Biography | I8: Biography - 551 | J8: 1 | K8: 552 | L8: 0.07 | M8: 513.36 | N8: 513.36 | O8: 0.4 | P8: 205.34 | Q8: Cash | R8: Delivered | S8: 6 | T8: 2024 | U8: Jan | V8: 1 | W8: 2024-01 | X8: 308.02 | Y8: Standard | Z8: Profitable | AA8: Mid Value
A9: Ord1388 | B9: 45315 | C9: Sara Khan | D9: East | E9: India | F9: London | G9: Electronics | H9: Laptop | I9: Laptop - 328 | J9: 9 | K9: 78008 | L9: 0.13 | M9: 67866.96 | N9: 610802.64 | O9: 0.15 | P9: 91620.4 | Q9: Cash | R9: Delivered | S9: 5 | T9: 2024 | U9: Jan | V9: 1 | W9: 2024-01 | X9: 519182.24 | Y9: Standard | Z9: Profitable | AA9: High Value
A10: Ord1115 | B10: 45042 | C10: Amit Verma | D10: North | E10: Usa | F10: Delhi | G10: Books | H10: Non-Fiction | I10: Non-Fiction - 673 | J10: 1 | K10: 659 | L10: 0.18 | M10: 540.38 | N10: 540.38 | O10: 0.4 | P10: 216.15 | Q10: Credit Card | R10: Delivered | S10: 5 | T10: 2023 | U10: Apr | V10: 4 | W10: 2023-04 | X10: 324.23 | Y10: Standard | Z10: Profitable | AA10: Mid Value
A11: Ord1071 | B11: 44998 | C11: David Lee | D11: East | E11: India | F11: Toronto | G11: Books | H11: Comics | I11: Comics - 276 | J11: 1 | K11: 619 | L11: 0.11 | M11: 550.91 | N11: 550.91 | O11: 0.4 | P11: 220.36 | Q11: Credit Card | R11: Delivered | S11: 9 | T11: 2023 | U11: Mar | V11: 3 | W11: 2023-03 | X11: 330.55 | Y11: Delayed | Z11: Profitable | AA11: Mid Value
A12: Ord1902 | B12: 45829 | C12: John Smith | D12: West | E12: Usa | F12: Toronto | G12: Books | H12: Fiction | I12: Fiction - 965 | J12: 1 | K12: 691 | L12: 0.17 | M12: 573.53 | N12: 573.53 | O12: 0.4 | P12: 229.41 | Q12: Credit Card | R12: Delivered | S12: 9 | T12: 2025 | U12: Jun | V12: 6 | W12: 2025-06 | X12: 344.12 | Y12: Delayed | Z12: Profitable | AA12: Mid Value
A13: Ord1412 | B13: 45339 | C13: Sara Khan | D13: North | E13: India | F13: Mumbai | G13: Books | H13: Biography | I13: Biography - 522 | J13: 2 | K13: 315 | L13: 0.05 | M13: 299.25 | N13: 598.5 | O13: 0.4 | P13: 239.4 | Q13: Cash | R13: Delivered | S13: 9 | T13: 2024 | U13: Feb | V13: 2 | W13: 2024-02 | X13: 359.1 | Y13: Delayed | Z13: Profitable | AA13: Mid Value
... A605: Ord1411 | B605: 45338 | C605: John Smith | D605: South | E605: India | F605: London | G605: Furniture | H605: Bookshelf | I605: Bookshelf - 115 | J605: 3 | K605: 16109 | L605: 0.19 | M605: 13048.29 | N605: 39144.87 | O605: 0.2 | P605: 7828.97 | Q605: UPI | R605: Delivered | S605: 8 | T605: 2024 | U605: Feb | V605: 2 | W605: 2024-02 | X605: 31315.9 | Y605: Delayed | Z605: Profitable | AA605: High Value

Sheet Calculations_Pivot_Table
A1: total_revenue | E1: Row Labels | F1: Sum of Sales | G1: Sum of Profit_Amount | K1: Row Labels | L1: Sum of Sales | N1: Row Labels | O1: Sum of Sales | T1: Row Labels | U1: Sum of Profit_Amount | V1: Sum of Sales
A2: 60714956 | C2: 50747229 | E2: Books | F2: 772284.36 | G2: 308913.69 | K2: Earphones - 181 | L2: 518577.36 | N2: East | O2: 17598171 | T2: 2023 | U2: 4197267 | V2: 23186470
A3: Total Profit | E3: Clothing | F3: 2193382.1 | G3: 767683.77 | K3: Laptop - 328 | L3: 610802.64 | N3: North | O3: 12093870 | T3: 2024 | U3: 3846825.2 | V3: 21430189
A4: 10952952 | C4: 8241682.1 | E4: Electronics | F4: 41244408 | G4: 6186661.2 | K4: Laptop - 923 | L4: 532378.9 | N4: South | O4: 18551131 | T4: 2025 | U4: 2908859.8 | V4: 16098297
A5: Average of Profit_Margin | E5: Furniture | F5: 8730536 | G5: 1746107.2 | K5: Mobile - 335 | L5: 609284.16 | N5: West | O5: 12471784 | T5: Grand Total | U5: 10952952 | V5: 60714956
A6: 0.2691 | C6: 0.25016556 | E6: Sports | F6: 7774344.9 | G6: 1943586.2 | K6: Mobile - 495 | L6: 526981.02 | N6: Grand Total | O6: 60714956
A7: Total Orders Processed | E7: Grand Total | F7: 60714956 | G7: 10952952 | K7: Mobile - 519 | L7: 584192.7
A8: 1000 | C8: 604 | K8: Mobile - 660 | L8: 558706.8
A9: Total Product sold | K9: Tablet - 401 | L9: 560867.16
A10: 5013 | C10: 3026 | K10: Tablet - 521 | L10: 544771.8
K11: Tablet - 556 | L11: 524106.36
K12: Grand Total | L12: 5570668.9

Sheet Dashboard 
B2: Sales and Product Performance
B3: Interactive analytics and KPI Tracking
